[
  {
    "title": "HTML",
    "imageSrc": "skills/html.png"
  },
  {
    "title": "CSS",
    "imageSrc": "skills/css.png"
  },
  {
    "title": "JavaScript",
    "imageSrc": "skills/javascript.png"
  },
  {
    "title": "React",
    "imageSrc": "skills/react.png"
  },
  {
    "title": "Node",
    "imageSrc": "skills/node.png"
  },
  {
    "title": "MongoDB",
    "imageSrc": "skills/mongodb.png"
  },
  {
    "title": "MySql",
    "imageSrc": "skills/mysql.png"
  },
  {
    "title": "Python",
    "imageSrc": "skills/python.png"
  },
  {
    "title": "PHP",
    "imageSrc": "skills/php.png"
  },
  {
    "title": "Kotlin",
    "imageSrc": "skills/Kotlin.png"
  },
  {
    "title": "Unity",
    "imageSrc": "skills/unity.png"
  },
  {
    "title": "Cisco Packet Tracer",
    "imageSrc": "skills/cisco.png"
  },
  {
    "title": "Wireshark",
    "imageSrc": "skills/wireshark.png"
  },
  {
    "title": "Nmap",
    "imageSrc": "skills/nmap.png"
  },
  {
    "title": "Burp Suite",
    "imageSrc": "skills/burp.png"
  },
  {
    "title": "Metasploit",
    "imageSrc": "skills/metasploit.png"
  },
  {
    "title": "Kali Linux",
    "imageSrc": "skills/kali.png"
  }
]
